README.md
setup.cfg
setup.py
anndb_api/__init__.py
anndb_api/client.py
anndb_api/dataset.py
anndb_api/images_dataset.py
anndb_api/text_dataset.py
anndb_api/util.py
anndb_api/vector_dataset.py
anndb_api.egg-info/PKG-INFO
anndb_api.egg-info/SOURCES.txt
anndb_api.egg-info/dependency_links.txt
anndb_api.egg-info/not-zip-safe
anndb_api.egg-info/requires.txt
anndb_api.egg-info/top_level.txt
anndb_api/anndb_api_pb/__init__.py
anndb_api/anndb_api_pb/core_pb2.py
anndb_api/anndb_api_pb/core_pb2_grpc.py
anndb_api/anndb_api_pb/image_dataset_pb2.py
anndb_api/anndb_api_pb/image_dataset_pb2_grpc.py
anndb_api/anndb_api_pb/text_dataset_pb2.py
anndb_api/anndb_api_pb/text_dataset_pb2_grpc.py
anndb_api/anndb_api_pb/vector_dataset_pb2.py
anndb_api/anndb_api_pb/vector_dataset_pb2_grpc.py