Metadata-Version: 1.1
Name: anndb-api
Version: 0.1.2
Summary: AnnDB API Client
Home-page: https://github.com/anndb-com/anndb-api-client-python
Author: Marek Galovic
Author-email: contact@anndb.com
License: Apache-2.0
Download-URL: https://github.com/anndb-com/anndb-api-client-python/archive/0.1.2.tar.gz
Platform: UNKNOWN
